clonf-0.4.1.dist-info/METADATA
clonf-0.4.1.dist-info/WHEEL
clonf-0.4.1.dist-info/entry_points.txt
clonf-0.4.1.dist-info/licenses/LICENSE
clonf/__init__.py
clonf/annotations.py
clonf/extractor.py
clonf/integrations/__init__.py
clonf/integrations/click/__init__.py
clonf/integrations/click/params.py
clonf/integrations/click/types.py
clonf/py.typed
clonf-0.4.1.dist-info/RECORD
