Metadata-Version: 2.1
Name: clonf
Version: 0.4.1
Summary: Declaratively connect cli and config definition using pydantic
Keywords: cli,click,pydantic,pydantic-settings,declarative,config
Author-Email: Jan Vollmer <jan@vllmr.dev>
License: MIT
Classifier: Framework :: Pydantic :: 2
Classifier: Intended Audience :: Developers
Classifier: License :: OSI Approved :: MIT License
Classifier: Programming Language :: Python :: 3.9
Classifier: Programming Language :: Python :: 3.10
Classifier: Programming Language :: Python :: 3.11
Classifier: Programming Language :: Python :: 3.12
Classifier: Programming Language :: Python :: 3.13
Classifier: Programming Language :: Python :: 3.14
Classifier: Typing :: Typed
Project-URL: Source, https://github.com/jvllmr/clonf
Requires-Python: >=3.9
Requires-Dist: pydantic>=2.12.3
Requires-Dist: typing-extensions>=4.15.0
Provides-Extra: click
Requires-Dist: click>=8.1.8; extra == "click"
Provides-Extra: settings
Requires-Dist: pydantic-settings>=2.11.0; extra == "settings"
Provides-Extra: all
Requires-Dist: click>=8.1.8; extra == "all"
Requires-Dist: pydantic-settings>=2.11.0; extra == "all"
